otel_output_parser/__init__.py
otel_output_parser/cli_generate_static_data.py
otel_output_parser/cli_pynb_log_parser.py
otel_output_parser/mermaid_graphs.py
otel_output_parser/common_helpers/__init__.py
otel_output_parser/common_helpers/github_helpers.py
otel_output_parser/common_helpers/utils.py
otel_output_parser/static_builder/__init__.py
pynb_dag_runner/__init__.py
pynb_dag_runner/__version__.py
pynb_dag_runner/helpers.py
pynb_dag_runner/notebooks_helpers.py
pynb_dag_runner/opentelemetry_helpers.py
pynb_dag_runner/opentelemetry_task_span_parser.py
pynb_dag_runner/ray_helpers.py
pynb_dag_runner/ray_mypy_helpers.py
pynb_dag_runner/run_pipeline_helpers.py
pynb_dag_runner/core/__init__.py
pynb_dag_runner/core/dag_runner.py
pynb_dag_runner/tasks/__init__.py
pynb_dag_runner/tasks/task_opentelemetry_logging.py
pynb_dag_runner/tasks/tasks.py
pynb_dag_runner_snapshot-0.0.9.dev1672416330.dist-info/METADATA
pynb_dag_runner_snapshot-0.0.9.dev1672416330.dist-info/WHEEL
pynb_dag_runner_snapshot-0.0.9.dev1672416330.dist-info/entry_points.txt
pynb_dag_runner_snapshot-0.0.9.dev1672416330.dist-info/top_level.txt
pynb_dag_runner_snapshot-0.0.9.dev1672416330.dist-info/RECORD
