Metadata-Version: 2.1
Name: pynb-dag-runner-snapshot
Version: 0.0.9.dev1672416330
Summary: UNKNOWN
Home-page: https://github.com/pynb-dag-runner/pynb-dag-runner
Author: Matias Dahl
Author-email: matias.dahl@iki.fi
License: MIT
Platform: UNKNOWN
Classifier: License :: OSI Approved :: MIT License
Requires-Dist: fastcore (==1.4.3)
Requires-Dist: ghapi (==0.1.19)
Requires-Dist: jupytext (==1.14.4)
Requires-Dist: notebook (==6.5.2)
Requires-Dist: opentelemetry-api (==1.15.0)
Requires-Dist: opentelemetry-exporter-otlp (==1.15.0)
Requires-Dist: opentelemetry-sdk (==1.15.0)
Requires-Dist: papermill (==2.4.0)
Requires-Dist: pydantic (==1.10.4)
Requires-Dist: python-dateutil (==2.8.2)
Requires-Dist: ray[default] (==2.2.0)
Requires-Dist: requests (==2.27.1)
